sql_deta/__init__.py
sql_deta/peewee.py
sql_deta-0.0.10a4.dist-info/LICENSE
sql_deta-0.0.10a4.dist-info/METADATA
sql_deta-0.0.10a4.dist-info/WHEEL
sql_deta-0.0.10a4.dist-info/top_level.txt
sql_deta-0.0.10a4.dist-info/RECORD
