Metadata-Version: 2.1
Name: sql-deta
Version: 0.0.10a4
Summary: Detabase <--> SQL proxy
Home-page: https://github.com/ablaternae/sql-deta
Author: d;)
License: GLWTPL
Keywords: deta,detabase,sql,peewee,mixin
Classifier: Development Status :: 3 - Alpha
Classifier: Intended Audience :: Developers
Classifier: License :: OSI Approved :: GNU Affero General Public License v3
Classifier: Operating System :: OS Independent
Classifier: Programming Language :: Python :: 3
Classifier: Programming Language :: Python :: 3.7
Classifier: Topic :: Software Development :: Libraries :: Python Modules
Requires-Python: >=3.7
License-File: LICENSE
Requires-Dist: deta
Requires-Dist: odetam
Requires-Dist: more-itertools
Requires-Dist: peewee
